hiktools/__init__.py
hiktools/csadp/CService.py
hiktools/csadp/__init__.py
hiktools/csadp/checksum.py
hiktools/csadp/model.py
hiktools/csadp/payloads.py
hiktools/csadp/uarray.py
hiktools/fmod/__init__.py
hiktools/fmod/__main__.py
hiktools/fmod/digicap.py
hiktools/fmod/export.py
hiktools/sadp/__init__.py
hiktools/sadp/client.py
hiktools/sadp/message.py
hiktools-1.2.2.dist-info/LICENSE
hiktools-1.2.2.dist-info/METADATA
hiktools-1.2.2.dist-info/WHEEL
hiktools-1.2.2.dist-info/top_level.txt
hiktools-1.2.2.dist-info/RECORD
