Metadata-Version: 2.1
Name: hiktools
Version: 1.2.2
Summary: Hikvision utility tools
Author-email: MatrixEditor <not@supported.com>
Project-URL: Homepage, https://github.com/MatrixEditor/hiktools
Project-URL: API-Docs, https://hiktools.readthedocs.io
Project-URL: Native-API-Docs, https://matrixeditor.github.io/hiktools/docs/html/d3/dcc/md__r_e_a_d_m_e.html
Classifier: Development Status :: 5 - Production/Stable
Classifier: Intended Audience :: Science/Research
Classifier: License :: OSI Approved :: MIT License
Classifier: Programming Language :: Python :: 3.6
Classifier: Programming Language :: Python :: 3.7
Classifier: Programming Language :: Python :: 3.8
Classifier: Programming Language :: Python :: 3.9
Classifier: Programming Language :: Python :: 3.10
License-File: LICENSE
